setup.py
src/batchcompute_sge/__init__.py
src/batchcompute_sge/const.py
src/batchcompute_sge.egg-info/PKG-INFO
src/batchcompute_sge.egg-info/SOURCES.txt
src/batchcompute_sge.egg-info/dependency_links.txt
src/batchcompute_sge.egg-info/entry_points.txt
src/batchcompute_sge.egg-info/requires.txt
src/batchcompute_sge.egg-info/top_level.txt
src/batchcompute_sge/actions/__init__.py
src/batchcompute_sge/actions/cluster.py
src/batchcompute_sge/actions/config.py
src/batchcompute_sge/actions/lists.py
src/batchcompute_sge/actions/login.py
src/batchcompute_sge/bin/__init__.py
src/batchcompute_sge/bin/bccluster.py
src/batchcompute_sge/bin/sge_bootstrap.py
src/batchcompute_sge/bin/sge_execd_watchdog.py
src/batchcompute_sge/bin/sge_master_watchdog
src/batchcompute_sge/bin/sge_master_watchdog.py
src/batchcompute_sge/bin/sge_refresh.py
src/batchcompute_sge/externals/__init__.py
src/batchcompute_sge/externals/command.py
src/batchcompute_sge/lib/__init__.py
src/batchcompute_sge/lib/batchcompute_client.py
src/batchcompute_sge/lib/bccluster_json.py
src/batchcompute_sge/lib/ecs_client.py
src/batchcompute_sge/lib/it_config.py
src/batchcompute_sge/lib/sge_common.py
src/batchcompute_sge/util/__init__.py
src/batchcompute_sge/util/debugger.py
src/batchcompute_sge/util/formatter.py
src/batchcompute_sge/util/list2table.py
src/batchcompute_sge/util/smart_unicode.py