Metadata-Version: 1.0
Name: batchcompute-sge
Version: 1.3.7a1
Summary: Alibaba Cloud BatchCompute SGE command line interface
Home-page: http://www.aliyun.com/product/batchcompute
Author: guangchun.luo
Author-email: guangchun.luo@alibaba-inc.com
License: MIT License
Keywords: batchcompute-sge,bcs-sge,sge
Platform: any
